MANIFEST.in
README.rst
VERSION
setup.py
hitchtest/__init__.py
hitchtest/arguments.py
hitchtest/commandline.py
hitchtest/executionengine.py
hitchtest/hitch_stacktrace.py
hitchtest/modified.py
hitchtest/module.py
hitchtest/package.py
hitchtest/result.py
hitchtest/results.py
hitchtest/scenario.py
hitchtest/schema.yaml
hitchtest/settings.py
hitchtest/signal_manager.py
hitchtest/snapdir.py
hitchtest/step.py
hitchtest/suite.py
hitchtest/test.py
hitchtest/utils.py
hitchtest.egg-info/PKG-INFO
hitchtest.egg-info/SOURCES.txt
hitchtest.egg-info/dependency_links.txt
hitchtest.egg-info/entry_points.txt
hitchtest.egg-info/not-zip-safe
hitchtest.egg-info/requires.txt
hitchtest.egg-info/top_level.txt
hitchtest/environment/__init__.py
hitchtest/environment/checks.py
hitchtest/environment/utils.py
hitchtest/environment/verifier.py
hitchtest/templates/default.jinja2
hitchtest/templates/json.jinja2
hitchtest/templates/stacktrace_default.jinja2